HISTORY.txt
MANIFEST.in
README.txt
TODO.txt
setup.cfg
setup.py
prdg/__init__.py
prdg.plone.util.egg-info/PKG-INFO
prdg.plone.util.egg-info/SOURCES.txt
prdg.plone.util.egg-info/dependency_links.txt
prdg.plone.util.egg-info/entry_points.txt
prdg.plone.util.egg-info/namespace_packages.txt
prdg.plone.util.egg-info/not-zip-safe
prdg.plone.util.egg-info/requires.txt
prdg.plone.util.egg-info/top_level.txt
prdg/plone/__init__.py
prdg/plone/util/__init__.py
prdg/plone/util/config.py
prdg/plone/util/structure.py
prdg/plone/util/testing.py
prdg/plone/util/users.py
prdg/plone/util/utils.py
prdg/plone/util/validators.py
prdg/plone/util/versioning.py
prdg/plone/util/tests/__init__.py
prdg/plone/util/tests/base.py
prdg/plone/util/tests/sample.png
prdg/plone/util/tests/test_file_extension_validator.py
prdg/plone/util/tests/test_structure.py
prdg/plone/util/tests/test_users.py
prdg/plone/util/tests/test_utils.py