Metadata-Version: 1.1
Name: prdg.plone.util
Version: 0.0.9
Summary: Assorted Plone utilities.
Home-page: UNKNOWN
Author: Rafael Oliveira
Author-email: rafaelbco@gmail.com
License: GPL
Keywords: plone util utilities
Platform: UNKNOWN
Classifier: Programming Language :: Python
Classifier: Topic :: Software Development :: Libraries :: Python Modules
